sigur_worker/__init__.py
sigur_worker/functions.py
sigur_worker/main.py
sigur_worker/mixins.py
sigur_worker/tests/__init__.py
sigur_worker/tests/main_tests.py
sigur_gate-0.0.1.dist-info/LICENSE
sigur_gate-0.0.1.dist-info/METADATA
sigur_gate-0.0.1.dist-info/WHEEL
sigur_gate-0.0.1.dist-info/top_level.txt
sigur_gate-0.0.1.dist-info/RECORD
