Metadata-Version: 2.1
Name: sigur-gate
Version: 0.0.1
Summary: UNKNOWN
Author: PunchyArchy
Author-email: ksmdrmvscthny@gmail.com
License: UNKNOWN
Platform: UNKNOWN
License-File: LICENSE
Requires-Dist: sigur-emulator
